<?xml version="1.0" encoding="UTF-8" ?>
<!DOCTYPE struts PUBLIC
	"-//Apache Software Foundation//DTD Struts Configuration 2.3//EN"
	"http://struts.apache.org/dtds/struts-2.3.dtd">

<struts>
	<package name="default" namespace="/" extends="struts-default">
		<action name="UserMange_*" class="UserMangeAction" method="{1}">
			<result name="alterUsername">/user/person.jsp</result>
			<result name="succesAlterUsername">/user/alterUsername.jsp</result>
			<result name="succesAlterPassword">/user/alterPassword.jsp</result>
			<result name="alterPassword">/user/succesAlterPassword.html</result>
		</action>
	</package>
</struts>